LICENSE
MANIFEST.in
README.rst
igv_api.py
setup.py
bin/igv
bin/igv_plotter
bin/igvweb_viewer
igv_plotter.egg-info/PKG-INFO
igv_plotter.egg-info/SOURCES.txt
igv_plotter.egg-info/dependency_links.txt
igv_plotter.egg-info/not-zip-safe
igv_plotter.egg-info/pbr.json
igv_plotter.egg-info/requires.txt
igv_plotter.egg-info/top_level.txt
lib/igv.jar
static/css/font-awesome.min.css
static/css/igv-1.0.1.css
static/css/jquery-ui.css
static/css/img/cursor_logo.png
static/css/img/cursor_logo.svg
static/css/img/igv_logo_letters_paths.svg
static/fonts/fontawesome-webfont.ttf
static/fonts/fontawesome-webfont.woff
static/img/cursor_logo.png
static/img/cursor_logo.svg
static/js/igv-1.0.1.js
static/js/igv.js
static/js/igv.min.js
static/js/igv.min.map
static/js/jquery-ui.min.js
static/js/jquery.min.js
tests/__init__.py
tests/__init__.pyc
tests/test_igv_api.py
tests/test_igv_api.pyc
tests/test_igv_plotter_script.pyc