Metadata-Version: 1.1
Name: igv-plotter
Version: 0.9.8.7
Summary: python interface to IGV that simplifies creating screenshots of BAMs, VCFs, BEDs, etc for one-off spot checking or automated / scripted image collection
Home-page: https://github.com/macarthur-lab/igv_utils
Author: Ben Weisburd
Author-email: weisburd@broadinstitute.org
License: MIT
Keywords: IGV,snapshots,screenshots,images,BAM,VCF,bioinformatics,sequencing,NGS,variants
Platform: UNKNOWN
Classifier: Development Status :: 4 - Beta
Classifier: Intended Audience :: Developers
Classifier: License :: OSI Approved :: MIT License
Classifier: Natural Language :: English
Classifier: Programming Language :: Python :: 2
Classifier: Programming Language :: Python :: 2.7
Classifier: Programming Language :: Python :: 3
Classifier: Programming Language :: Python :: 3.2
Classifier: Programming Language :: Python :: 3.3
Classifier: Programming Language :: Python :: 3.4
Classifier: Programming Language :: Python :: Implementation :: CPython
Classifier: Programming Language :: Python :: Implementation :: PyPy
